mgefit/CHANGELOG.rst
mgefit/LICENSE.txt
mgefit/README.rst
mgefit/__init__.py
mgefit/find_galaxy.py
mgefit/mge_fit_1d.py
mgefit/mge_fit_sectors.py
mgefit/mge_fit_sectors_regularized.py
mgefit/mge_fit_sectors_twist.py
mgefit/mge_print_contours.py
mgefit/mge_print_contours_twist.py
mgefit/readme_mge_fit_sectors.pdf
mgefit/sectors_photometry.py
mgefit/sectors_photometry_twist.py
mgefit/sky_level.py
mgefit/examples/__init__.py
mgefit/examples/mge_fit_example.py
mgefit/examples/mge_fit_example_python_reference_output.txt
mgefit/images/m32_f814w_pc.fits
mgefit/images/m32_i.fits
mgefit/images/ngc4342_f814w_pc.fits
mgefit/images/ngc5831_f702w_mosaic.fits
mgefit-6.1.5.dist-info/METADATA
mgefit-6.1.5.dist-info/WHEEL
mgefit-6.1.5.dist-info/top_level.txt
mgefit-6.1.5.dist-info/zip-safe
mgefit-6.1.5.dist-info/RECORD
